openbambucommands/__init__.py
openbambucommands/py.typed
openbambucommands/ftp/__init__.py
openbambucommands/ftp/hello.py
openbambucommands/mqtt/__init__.py
openbambucommands/mqtt/calibrate.py
openbambucommands/mqtt/get_version.py
openbambucommands/mqtt/ledctrl.py
openbambucommands/mqtt/print_pause.py
openbambucommands/mqtt/print_resume.py
openbambucommands/mqtt/print_stop.py
openbambucommands-0.4.3.dist-info/LICENSE
openbambucommands-0.4.3.dist-info/METADATA
openbambucommands-0.4.3.dist-info/WHEEL
openbambucommands-0.4.3.dist-info/top_level.txt
openbambucommands-0.4.3.dist-info/RECORD
