Metadata-Version: 2.1
Name: openbambucommands
Version: 0.4.3
Summary: A package that provides helper functions for generating BambuLabs printer commands
Author-email: wolfy <wolfy@shitwolfymakes.com>
Project-URL: Homepage, https://github.com/shitwolfymakes/openbambucommands
Project-URL: Bug Tracker, https://github.com/shitwolfymakes/openbambucommands/issues
Classifier: License :: OSI Approved :: MIT License
Classifier: Operating System :: OS Independent
Classifier: Programming Language :: Python :: 3
Classifier: Programming Language :: Python :: 3.7
Classifier: Programming Language :: Python :: 3.8
Classifier: Programming Language :: Python :: 3.9
Classifier: Programming Language :: Python :: 3.10
Classifier: Programming Language :: Python :: 3.11
Requires-Python: >=3.7
License-File: LICENSE
Provides-Extra: dev
Requires-Dist: black ; extra == 'dev'
Requires-Dist: docformatter[toml] ; extra == 'dev'
Requires-Dist: flake8 ; extra == 'dev'
Requires-Dist: isort ; extra == 'dev'
Requires-Dist: mypy ; extra == 'dev'
Requires-Dist: pre-commit ; extra == 'dev'
Requires-Dist: pytest ; extra == 'dev'
Requires-Dist: pytest-cov ; extra == 'dev'
